README.md
setup.cfg
setup.py
logicdrop/__init__.py
logicdrop/sparks/__init__.py
logicdrop/sparks/openapi/__init__.py
logicdrop/sparks/openapi/api_client.py
logicdrop/sparks/openapi/configuration.py
logicdrop/sparks/openapi/exceptions.py
logicdrop/sparks/openapi/rest.py
logicdrop/sparks/openapi/api/__init__.py
logicdrop/sparks/openapi/api/admin_services_api.py
logicdrop/sparks/openapi/api/cache_services_api.py
logicdrop/sparks/openapi/api/client_services_api.py
logicdrop/sparks/openapi/api/compute_services_api.py
logicdrop/sparks/openapi/api/content_services_api.py
logicdrop/sparks/openapi/api/data_services_api.py
logicdrop/sparks/openapi/api/email_services_api.py
logicdrop/sparks/openapi/api/kiosk_services_api.py
logicdrop/sparks/openapi/api/office_services_api.py
logicdrop/sparks/openapi/api/package_services_api.py
logicdrop/sparks/openapi/api/platform_services_api.py
logicdrop/sparks/openapi/api/project_services_api.py
logicdrop/sparks/openapi/api/query_services_api.py
logicdrop/sparks/openapi/api/schema_services_api.py
logicdrop/sparks/openapi/api/security_services_api.py
logicdrop/sparks/openapi/api/template_services_api.py
logicdrop/sparks/openapi/models/__init__.py
logicdrop/sparks/openapi/models/artifact_reference.py
logicdrop/sparks/openapi/models/artifact_response.py
logicdrop/sparks/openapi/models/assertion.py
logicdrop/sparks/openapi/models/between_query_field.py
logicdrop/sparks/openapi/models/between_query_field_all_of.py
logicdrop/sparks/openapi/models/bundle.py
logicdrop/sparks/openapi/models/cache_request.py
logicdrop/sparks/openapi/models/cache_request_value.py
logicdrop/sparks/openapi/models/cache_result.py
logicdrop/sparks/openapi/models/client.py
logicdrop/sparks/openapi/models/client_registration.py
logicdrop/sparks/openapi/models/client_settings.py
logicdrop/sparks/openapi/models/compute_options.py
logicdrop/sparks/openapi/models/compute_rule.py
logicdrop/sparks/openapi/models/compute_ruleset.py
logicdrop_sparks_openapi.egg-info/PKG-INFO
logicdrop_sparks_openapi.egg-info/SOURCES.txt
logicdrop_sparks_openapi.egg-info/dependency_links.txt
logicdrop_sparks_openapi.egg-info/requires.txt
logicdrop_sparks_openapi.egg-info/top_level.txt