Metadata-Version: 1.0
Name: logicdrop-sparks-openapi
Version: 4.3.1
Summary: Sparks OpenAPI
Home-page: UNKNOWN
Author: Support
Author-email: support@logicdrop.com
License: UNKNOWN
Keywords: OpenAPI,OpenAPI-Generator,Sparks OpenAPI
Platform: UNKNOWN
